retrix/__init__.py
retrix-0.0.0.dist-info/LICENSE
retrix-0.0.0.dist-info/METADATA
retrix-0.0.0.dist-info/WHEEL
retrix-0.0.0.dist-info/top_level.txt
retrix-0.0.0.dist-info/RECORD
