Metadata-Version: 2.1
Name: retrix
Version: 0.0.0
Summary: Pythonic Econometrics for Reproducible Research
Home-page: https://github.com/kiss-oliver/metrix
Author: Oliver Kiss
Author-email: python-metrix@protonmail.com
License: UNKNOWN
Project-URL: Bug Tracker, https://github.com/kiss-oliver/metrix/issues
Platform: UNKNOWN
Classifier: Programming Language :: Python :: 3
Classifier: License :: OSI Approved :: GNU General Public License v3 (GPLv3)
Classifier: Operating System :: OS Independent
Requires-Python: >=3.6
License-File: LICENSE
